nrclex.py
NRCLex-4.0.dist-info/LICENSE
NRCLex-4.0.dist-info/METADATA
NRCLex-4.0.dist-info/WHEEL
NRCLex-4.0.dist-info/top_level.txt
NRCLex-4.0.dist-info/RECORD
