Metadata-Version: 2.1
Name: NRCLex
Version: 4.0
Summary: An affect generator based on TextBlob and the NRC affect lexicon.  Note that lexicon license is for research purposes only.
Home-page: https://github.com/metalcorebear/NRCLex
Author: metalcorebear
Author-email: mark.mbailey@gmail.com
License: UNKNOWN
Platform: UNKNOWN
Classifier: Programming Language :: Python :: 3.9
Classifier: License :: OSI Approved :: MIT License
Classifier: Operating System :: OS Independent
Requires-Python: >=2.7
License-File: LICENSE
Requires-Dist: textblob
Requires-Dist: collections
Requires-Dist: json
